xwolfx/__init__.py
xwolfx/client/__init__.py
xwolfx/client/wolf.py
xwolfx/commands/__init__.py
xwolfx/commands/command.py
xwolfx/commands/command_handler.py
xwolfx/constants/__init__.py
xwolfx/constants/login_type.py
xwolfx/constants/online_state.py
xwolfx/models/__init__.py
xwolfx/models/base.py
xwolfx/models/command_context.py
xwolfx/models/message.py
xwolfx-1.0.1.dist-info/licenses/LICENSE
xwolfx-1.0.1.dist-info/METADATA
xwolfx-1.0.1.dist-info/WHEEL
xwolfx-1.0.1.dist-info/top_level.txt
xwolfx-1.0.1.dist-info/RECORD
